{
  "mappings": {
    "properties": {
      "time": {
        "type": "date"
      },
      "vendor": {
        "type": "keyword"
      },
      "endpoint": {
        "type": "keyword"
      },
      "relayMode": {
        "type": "keyword"
      },
      "deviceTokenHash": {
        "type": "keyword"
      },
      "requestTokens": {
        "type": "integer"
      },
      "responseTokens": {
        "type": "integer"
      },
      "requestNumMessages": {
        "type": "integer"
      },
      "requestNumUserMessages": {
        "type": "integer"
      },
      "requestMessage": {
        "type": "text",
        "fielddata": true
      },
      "responseMessage": {
        "type": "text",
        "fielddata": true
      },
      "cancelled": {
        "type": "boolean"
      },
      "completed": {
        "type": "boolean"
      },
      "error": {
        "type": "text",
        "fielddata": true
      },
      "sstFinalizationTime": {
        "type": "long"
      },
      "requestPreparationTime": {
        "type": "long"
      },
      "firstResponseTime": {
        "type": "long"
      },
      "ttsPreparationTime": {
        "type": "long"
      },
      "firstUtteranceTime": {
        "type": "long"
      },
      "totalTtsTime": {
        "type": "long"
      },
      "totalClickToSpeechTime": {
        "type": "long"
      },
      "totalResponseTime": {
        "type": "long"
      }
    }
  }
}